casrel_datautils/Base_Conf.py
casrel_datautils/__init__.py
casrel_datautils/casrel_model.py
casrel_datautils/data_loader.py
casrel_datautils/new_data_processor.py
casrel_datautils/process.py
tests/__init__.py
tests/tools_demo_已测.py
casrel_datautils_huli-2.1.8.dist-info/METADATA
casrel_datautils_huli-2.1.8.dist-info/WHEEL
casrel_datautils_huli-2.1.8.dist-info/top_level.txt
casrel_datautils_huli-2.1.8.dist-info/RECORD
